textevaluator/__init__.py
textevaluator/model.py
textevaluator/data/data.json
textevaluator/data/my_model.h5
textevaluator-0.4.dist-info/METADATA
textevaluator-0.4.dist-info/WHEEL
textevaluator-0.4.dist-info/entry_points.txt
textevaluator-0.4.dist-info/top_level.txt
textevaluator-0.4.dist-info/RECORD
